// class version 52.0 (52)
// access flags 0x21
public class Hello {

  // compiled from: Hello.java

  // access flags 0x1
  public <init>()V
   L0
    LINENUMBER 1 L0
    ALOAD 0
    INVOKESPECIAL java/lang/Object.<init> ()V
    RETURN
   L1
    LOCALVARIABLE this LHello; L0 L1 0
    MAXSTACK = 1
    MAXLOCALS = 1

  // access flags 0x9
  public static main([Ljava/lang/String;)V
   L0
    LINENUMBER 3 L0
    ICONST_1
    ISTORE 1
   L1
    LINENUMBER 4 L1
    LDC 2.0
    DSTORE 2
   L2
    LINENUMBER 5 L2
    LDC 3
    LSTORE 4
   L3
    LINENUMBER 6 L3
    ICONST_4
    ISTORE 6
   L4
    LINENUMBER 7 L4
    LDC ""
    INVOKEVIRTUAL java/lang/String.length ()I
    BIPUSH 10
    IF_ICMPGE L5
   L6
    LINENUMBER 9 L6
    GETSTATIC java/lang/System.out : Ljava/io/PrintStream;
    NEW java/lang/StringBuilder
    DUP
    INVOKESPECIAL java/lang/StringBuilder.<init> ()V
    LDC "\u9519\u8bef\u7528\u6cd5: num2 + num3 = "
    INVOKEVIRTUAL java/lang/StringBuilder.append (Ljava/lang/String;)Ljava/lang/StringBuilder;
    DLOAD 2
    INVOKEVIRTUAL java/lang/StringBuilder.append (D)Ljava/lang/StringBuilder;
    LLOAD 4
    INVOKEVIRTUAL java/lang/StringBuilder.append (J)Ljava/lang/StringBuilder;
    INVOKEVIRTUAL java/lang/StringBuilder.toString ()Ljava/lang/String;
    INVOKEVIRTUAL java/io/PrintStream.println (Ljava/lang/String;)V
   L5
    LINENUMBER 11 L5
   FRAME FULL [[Ljava/lang/String; I D J I] []
    ICONST_0
    ISTORE 7
   L7
   FRAME APPEND [I]
    ILOAD 7
    ILOAD 1
    IF_ICMPGE L8
   L9
    LINENUMBER 13 L9
    GETSTATIC java/lang/System.out : Ljava/io/PrintStream;
    LDC "\u56db\u5219\u8fd0\u7b97: num1 * num4 = "
    INVOKEVIRTUAL java/io/PrintStream.print (Ljava/lang/String;)V
   L10
    LINENUMBER 14 L10
    GETSTATIC java/lang/System.out : Ljava/io/PrintStream;
    ILOAD 1
    ILOAD 6
    IMUL
    INVOKEVIRTUAL java/io/PrintStream.println (I)V
   L11
    LINENUMBER 11 L11
    IINC 7 1
    GOTO L7
   L8
    LINENUMBER 16 L8
   FRAME CHOP 1
    RETURN
   L12
    LOCALVARIABLE i I L7 L8 7
    LOCALVARIABLE args [Ljava/lang/String; L0 L12 0
    LOCALVARIABLE num1 I L1 L12 1
    LOCALVARIABLE num2 D L2 L12 2
    LOCALVARIABLE num3 J L3 L12 4
    LOCALVARIABLE num4 B L4 L12 6
    MAXSTACK = 4
    MAXLOCALS = 8
}
